Metadata-Version: 1.1
Name: folder-clean
Version: 1.2.7
Summary: This library allows a user to specify which items (folders/files) that should be excluded from a folder clean.
Home-page: https://github.com/mrconter1/folder_clean
Author: Kjell Klark
Author-email: mrconter1@gmail.com
License: MPL-2.0
Platform: UNKNOWN
Classifier: Development Status :: 5 - Production/Stable
Classifier: Programming Language :: Python :: 2.7
Classifier: Programming Language :: Python :: 3.6
